task_recurrence/__init__.py
task_recurrence/task_recurrence.py
task_recurrence/tests/__init__.py
task_recurrence/tests/test_task_recurrence.py
task_recurrence-4.0.0.dist-info/WHEEL
task_recurrence-4.0.0.dist-info/METADATA
task_recurrence-4.0.0.dist-info/RECORD
