Metadata-Version: 2.1
Name: task-recurrence
Version: 4.0.0
Summary: A Recurrence library for todo applications that provide next date calculation and string generation
License: GPL-3.0+
Author: BeatLink
Author-email: beatlink@protonmail.com
Requires-Python: >=3.6,<4.0
Classifier: License :: OSI Approved :: GNU General Public License v3 or later (GPLv3+)
Classifier: Programming Language :: Python :: 3
Classifier: Programming Language :: Python :: 3.6
Classifier: Programming Language :: Python :: 3.7
Requires-Dist: arrow (>=0.14.7,<0.15.0)
